specio_py310/__init__.py
specio_py310/_version.py
specio_py310/cli.py
specio_py310/core/__init__.py
specio_py310/core/exceptions.py
specio_py310/core/format.py
specio_py310/core/functions.py
specio_py310/core/request.py
specio_py310/core/util.py
specio_py310/core/tests/__init__.py
specio_py310/core/tests/test_format.py
specio_py310/core/tests/test_functions.py
specio_py310/core/tests/test_request.py
specio_py310/core/tests/test_util.py
specio_py310/datasets/__init__.py
specio_py310/datasets/path.py
specio_py310/plugins/__init__.py
specio_py310/plugins/csv.py
specio_py310/plugins/example.py
specio_py310/plugins/fsm.py
specio_py310/plugins/mzml.py
specio_py310/plugins/mzxml.py
specio_py310/plugins/sp.py
specio_py310/plugins/spc.py
specio_py310/plugins/tests/__init__.py
specio_py310/plugins/tests/test_common.py
specio_py310/plugins/tests/test_example.py
specio_py310/plugins/tests/test_mzml.py
specio_py310/plugins/tests/test_spc.py
specio_py310/tests/__init__.py
specio_py310/tests/test_cli.py
specio_py310/tests/data/__init__.py
specio_py310/tests/data/sp1.spc
specio_py310/tests/data/sp2.spc
specio_py310/tests/data/sp3.spc
specio_py310/tests/data/spectra.mzml
specio_py310/tests/data/__pycache__/__init__.cpython-311.pyc
specio_py310-0.1.0.post2.data/data/specio_py310/tests/data/__init__.py
specio_py310-0.1.0.post2.data/data/specio_py310/tests/data/sp1.spc
specio_py310-0.1.0.post2.data/data/specio_py310/tests/data/sp2.spc
specio_py310-0.1.0.post2.data/data/specio_py310/tests/data/sp3.spc
specio_py310-0.1.0.post2.data/data/specio_py310/tests/data/spectra.mzml
specio_py310-0.1.0.post2.data/data/specio_py310/tests/data/__pycache__/__init__.cpython-311.pyc
specio_py310-0.1.0.post2.dist-info/LICENSE
specio_py310-0.1.0.post2.dist-info/METADATA
specio_py310-0.1.0.post2.dist-info/WHEEL
specio_py310-0.1.0.post2.dist-info/entry_points.txt
specio_py310-0.1.0.post2.dist-info/top_level.txt
specio_py310-0.1.0.post2.dist-info/RECORD
