Metadata-Version: 2.1
Name: specio-py310
Version: 0.1.0.post2
Summary: specio_py310: Python input/output for spectroscopic files. A modified version of SpecIO for Python 3.10+ compatibility
Home-page: https://github.com/BjornMelin/specio-py310
Download-URL: https://github.com/BjornMelin/specio-py310/archive/refs/tags/0.1.0.post2.tar.gz
Author: Guillaume Lemaitre
Author-email: g.lemaitre58@gmail.com
Maintainer: Bjorn Melin
Maintainer-email: bjornmelin16@gmail.com
License: BSD3
Platform: OS Independent
Classifier: Environment :: Console
Classifier: Intended Audience :: Science/Research
Classifier: License :: OSI Approved
Classifier: Operating System :: OS Independent
Classifier: Programming Language :: Python :: 2.7
Classifier: Programming Language :: Python :: 3.5
Classifier: Programming Language :: Python :: 3.6
Classifier: Programming Language :: Python :: 3.7
Classifier: Programming Language :: Python :: 3.8
Classifier: Programming Language :: Python :: 3.9
Classifier: Programming Language :: Python :: 3.10
Classifier: Programming Language :: Python :: 3.11
Classifier: Programming Language :: Python :: 3.12
Classifier: Topic :: Scientific/Engineering
License-File: LICENSE
Requires-Dist: numpy >=1.20
Requires-Dist: six
Provides-Extra: docs
Requires-Dist: sphinx >=4.0 ; extra == 'docs'
Requires-Dist: sphinx-gallery ; extra == 'docs'
Requires-Dist: sphinx-rtd-theme ; extra == 'docs'
Requires-Dist: numpydoc ; extra == 'docs'
Requires-Dist: matplotlib ; extra == 'docs'
Provides-Extra: tests
Requires-Dist: pytest >=6.0 ; extra == 'tests'
Requires-Dist: pytest-cov ; extra == 'tests'
Requires-Dist: pytest-mock ; extra == 'tests'
